fuelclient/__init__.py
fuelclient/client.py
fuelclient/consts.py
fuelclient/fuel_client.yaml
fuelclient/fuelclient_settings.py
fuelclient/hooks.py
fuelclient/main.py
fuelclient/profiler.py
fuelclient/utils.py
fuelclient/cli/__init__.py
fuelclient/cli/arguments.py
fuelclient/cli/error.py
fuelclient/cli/formatting.py
fuelclient/cli/parser.py
fuelclient/cli/serializers.py
fuelclient/cli/actions/__init__.py
fuelclient/cli/actions/base.py
fuelclient/cli/actions/deploy.py
fuelclient/cli/actions/deployment_tasks.py
fuelclient/cli/actions/environment.py
fuelclient/cli/actions/fact.py
fuelclient/cli/actions/fuelversion.py
fuelclient/cli/actions/graph.py
fuelclient/cli/actions/health.py
fuelclient/cli/actions/interrupt.py
fuelclient/cli/actions/network.py
fuelclient/cli/actions/network_group.py
fuelclient/cli/actions/node.py
fuelclient/cli/actions/nodegroup.py
fuelclient/cli/actions/notifications.py
fuelclient/cli/actions/openstack_config.py
fuelclient/cli/actions/plugins.py
fuelclient/cli/actions/release.py
fuelclient/cli/actions/role.py
fuelclient/cli/actions/settings.py
fuelclient/cli/actions/snapshot.py
fuelclient/cli/actions/token.py
fuelclient/cli/actions/user.py
fuelclient/cli/actions/vip.py
fuelclient/commands/__init__.py
fuelclient/commands/base.py
fuelclient/commands/environment.py
fuelclient/commands/extension.py
fuelclient/commands/fuelversion.py
fuelclient/commands/graph.py
fuelclient/commands/health.py
fuelclient/commands/network_group.py
fuelclient/commands/network_template.py
fuelclient/commands/node.py
fuelclient/commands/openstack_config.py
fuelclient/commands/plugins.py
fuelclient/commands/release.py
fuelclient/commands/role.py
fuelclient/commands/sequence.py
fuelclient/commands/snapshot.py
fuelclient/commands/tag.py
fuelclient/commands/task.py
fuelclient/commands/vip.py
fuelclient/common/__init__.py
fuelclient/common/data_utils.py
fuelclient/objects/__init__.py
fuelclient/objects/base.py
python_fuelclient-11.0.0.dist-info/DESCRIPTION.rst
python_fuelclient-11.0.0.dist-info/METADATA
python_fuelclient-11.0.0.dist-info/RECORD
python_fuelclient-11.0.0.dist-info/WHEEL
python_fuelclient-11.0.0.dist-info/entry_points.txt
python_fuelclient-11.0.0.dist-info/metadata.json
python_fuelclient-11.0.0.dist-info/pbr.json
python_fuelclient-11.0.0.dist-info/top_level.txt
