Metadata-Version: 2.0
Name: python-fuelclient
Version: 11.0.0
Summary: Command line interface and Python API wrapper for Fuel.
Home-page: https://docs.fuel-infra.org/fuel-dev
Author: Mirantis Inc.
Author-email: product@mirantis.com
License: UNKNOWN
Platform: UNKNOWN
Classifier: Environment :: OpenStack
Classifier: Intended Audience :: Information Technology
Classifier: Intended Audience :: System Administrators
Classifier: License :: OSI Approved :: Apache Software License
Classifier: Operating System :: POSIX :: Linux
Classifier: Programming Language :: Python
Classifier: Programming Language :: Python :: 2
Classifier: Programming Language :: Python :: 2.7
Classifier: Programming Language :: Python :: 3
Classifier: Programming Language :: Python :: 3.4
Requires-Dist: PyYAML (>=3.1.0)
Requires-Dist: cliff (!=1.16.0,>=1.15.0)
Requires-Dist: oslo.utils (>=3.5.0)
Requires-Dist: pbr (>=1.6)
Requires-Dist: python-keystoneclient (>=1.6.0,!=1.8.0,!=2.1.0)
Requires-Dist: requests (>=2.8.1,!=2.9.0)
Requires-Dist: six (>=1.9.0)
